pychology/__init__.py
pychology/behavior_trees.py
pychology-0.1a0.dist-info/LICENSE
pychology-0.1a0.dist-info/METADATA
pychology-0.1a0.dist-info/WHEEL
pychology-0.1a0.dist-info/top_level.txt
pychology-0.1a0.dist-info/RECORD
