Metadata-Version: 2.1
Name: pychology
Version: 0.1a0
Summary: Game AI algorithms in pure Python
Home-page: https://github.com/TheCheapestPixels/pychology
Author: TheCheapestPixels
Author-email: TheCheapestPixels@gmail.com
License: UNKNOWN
Project-URL: Source, https://github.com/TheCheapestPixels/pychology
Keywords: behavior tree
Platform: UNKNOWN
Classifier: Development Status :: 3 - Alpha
Classifier: Intended Audience :: Developers
Requires-Python: >=3.6, <4
